md410_2021_conv_common_online/__init__.py
md410_2021_conv_common_online/clear.py
md410_2021_conv_common_online/constants.py
md410_2021_conv_common_online/db.py
md410_2021_conv_common_online/email_2020_payees.py
md410_2021_conv_common_online/email_msg.txt
md410_2021_conv_common_online/test.py
md410_2021_conv_common_online-1.4.0.dist-info/WHEEL
md410_2021_conv_common_online-1.4.0.dist-info/METADATA
md410_2021_conv_common_online-1.4.0.dist-info/RECORD
