Metadata-Version: 2.1
Name: md410-2021-conv-common-online
Version: 1.4.0
Summary: Common libraries for applications related to the 2021 Lions MD410 Online Convention
Home-page: https://gitlab.com/md410_2021_conv/md410_2021_conv_common_online
Author: Kim van Wyk
Author-email: vanwykk@gmail.com
Requires-Python: >=3.7,<4.0
Classifier: Programming Language :: Python :: 3
Classifier: Programming Language :: Python :: 3.7
Classifier: Programming Language :: Python :: 3.8
Requires-Dist: black (>=19.10b0,<20.0)
Requires-Dist: psycopg2-binary (>=2.8.4,<3.0.0)
Requires-Dist: sqlalchemy (>=1.3.12,<2.0.0)
Project-URL: Repository, https://gitlab.com/md410_2021_conv/md410_2021_conv_common_online
